obs_switch/__init__.py
obs_switch/async_consumer.py
obs_switch/async_producer.py
obs_switch/cli.py
obs_switch/example_producer.py
obs_switch/obs_controller.py
obs_switch/runner.py
obs_switch/switch_controller.py
obs_switch/switch_handler.py
obs_switch-0.0.3.dist-info/licenses/LICENSE
obs_switch-0.0.3.dist-info/METADATA
obs_switch-0.0.3.dist-info/WHEEL
obs_switch-0.0.3.dist-info/entry_points.txt
obs_switch-0.0.3.dist-info/top_level.txt
obs_switch-0.0.3.dist-info/RECORD
