Metadata-Version: 2.4
Name: obs_switch
Version: 0.0.3
Summary: OBS Studio and Nintendo Switch controller integration via Kafka
Home-page: https://github.com/Splatoon-Stronghold/obs-switch
Author: Jason Jiménez Cruz
Author-email: jasonjimenezcruz@gmail.com
Classifier: Programming Language :: Python :: 3
Classifier: License :: OSI Approved :: MIT License
Classifier: Operating System :: OS Independent
Requires-Python: >=3.8
License-File: LICENSE
Requires-Dist: confluent-kafka>=2.0.0
Requires-Dist: python-dotenv==1.1.1
Requires-Dist: websocket-client==1.7.0
Requires-Dist: python-engineio==4.5.1
Requires-Dist: python-socketio==5.8.0
Requires-Dist: simple-websocket==1.1.0
Requires-Dist: argparse>=1.4.0
Requires-Dist: typing-extensions>=4.0.0
Requires-Dist: requests==2.32.4
Dynamic: author
Dynamic: author-email
Dynamic: classifier
Dynamic: description
Dynamic: description-content-type
Dynamic: home-page
Dynamic: license-file
Dynamic: requires-dist
Dynamic: requires-python
Dynamic: summary
